<?xml version="1.0" encoding="UTF-8" ?>
<!DOCTYPE mapper PUBLIC "-//mybatis.org//DTD Mapper 3.0//EN" "http://mybatis.org/dtd/mybatis-3-mapper.dtd" >
<mapper namespace="com.fashionsuperman.fs.game.dao.mapper.UserShareMapper" >
  <resultMap id="BaseResultMap" type="com.fashionsuperman.fs.game.dao.entity.UserShare" >
    <!--
      WARNING - @mbggenerated
      This element is automatically generated by MyBatis Generator, do not modify.
      This element was generated on Wed Aug 02 19:59:39 CST 2017.
    -->
    <id column="UserId" property="userid" jdbcType="BIGINT" />
    <result column="Flag" property="flag" jdbcType="VARCHAR" />
  </resultMap>
  <sql id="Base_Column_List" >
    <!--
      WARNING - @mbggenerated
      This element is automatically generated by MyBatis Generator, do not modify.
      This element was generated on Wed Aug 02 19:59:39 CST 2017.
    -->
    UserId, Flag
  </sql>
  <select id="selectByPrimaryKey" resultMap="BaseResultMap" parameterType="java.lang.Long" >
    <!--
      WARNING - @mbggenerated
      This element is automatically generated by MyBatis Generator, do not modify.
      This element was generated on Wed Aug 02 19:59:39 CST 2017.
    -->
    select 
    <include refid="Base_Column_List" />
    from usershare
    where UserId = #{userid,jdbcType=BIGINT}
  </select>
  <delete id="deleteByPrimaryKey" parameterType="java.lang.Long" >
    <!--
      WARNING - @mbggenerated
      This element is automatically generated by MyBatis Generator, do not modify.
      This element was generated on Wed Aug 02 19:59:39 CST 2017.
    -->
    delete from usershare
    where UserId = #{userid,jdbcType=BIGINT}
  </delete>
  <insert id="insert" parameterType="com.fashionsuperman.fs.game.dao.entity.UserShare" >
    <!--
      WARNING - @mbggenerated
      This element is automatically generated by MyBatis Generator, do not modify.
      This element was generated on Wed Aug 02 19:59:39 CST 2017.
    -->
    insert into usershare (UserId, Flag)
    values (#{userid,jdbcType=BIGINT}, #{flag,jdbcType=VARCHAR})
  </insert>
  <insert id="insertSelective" parameterType="com.fashionsuperman.fs.game.dao.entity.UserShare" >
    <!--
      WARNING - @mbggenerated
      This element is automatically generated by MyBatis Generator, do not modify.
      This element was generated on Wed Aug 02 19:59:39 CST 2017.
    -->
    insert into usershare
    <trim prefix="(" suffix=")" suffixOverrides="," >
      <if test="userid != null" >
        UserId,
      </if>
      <if test="flag != null" >
        Flag,
      </if>
    </trim>
    <trim prefix="values (" suffix=")" suffixOverrides="," >
      <if test="userid != null" >
        #{userid,jdbcType=BIGINT},
      </if>
      <if test="flag != null" >
        #{flag,jdbcType=VARCHAR},
      </if>
    </trim>
  </insert>
  <update id="updateByPrimaryKeySelective" parameterType="com.fashionsuperman.fs.game.dao.entity.UserShare" >
    <!--
      WARNING - @mbggenerated
      This element is automatically generated by MyBatis Generator, do not modify.
      This element was generated on Wed Aug 02 19:59:39 CST 2017.
    -->
    update usershare
    <set >
      <if test="flag != null" >
        Flag = #{flag,jdbcType=VARCHAR},
      </if>
    </set>
    where UserId = #{userid,jdbcType=BIGINT}
  </update>
  <update id="updateByPrimaryKey" parameterType="com.fashionsuperman.fs.game.dao.entity.UserShare" >
    <!--
      WARNING - @mbggenerated
      This element is automatically generated by MyBatis Generator, do not modify.
      This element was generated on Wed Aug 02 19:59:39 CST 2017.
    -->
    update usershare
    set Flag = #{flag,jdbcType=VARCHAR}
    where UserId = #{userid,jdbcType=BIGINT}
  </update>
</mapper>